{
  "project_info": {
    "project_number": "327113598022",
    "project_id": "fir-db-cff9f",
    "storage_bucket": "fir-db-cff9f.appspot.com"
  },
  "client": [
    {
      "client_info": {
        "mobilesdk_app_id": "1:327113598022:android:6167ca8c7be1cba66e9647",
        "android_client_info": {
          "package_name": "crud.firebase"
        }
      },
      "oauth_client": [
        {
          "client_id": "327113598022-d9meut6dod0ohn1p5ljcsgagonl4soub.apps.googleusercontent.com",
          "client_type": 3
        }
      ],
      "api_key": [
        {
          "current_key": "AIzaSyBxhPuYJ-nzfPsl2py_C60uUrau_i5O6NY"
        }
      ],
      "services": {
        "appinvite_service": {
          "other_platform_oauth_client": [
            {
              "client_id": "327113598022-d9meut6dod0ohn1p5ljcsgagonl4soub.apps.googleusercontent.com",
              "client_type": 3
            }
          ]
        }
      }
    }
  ],
  "configuration_version": "1"
}